{
    "MoveToPlayer": {
        "checkpoints": [
            {
                "steps": 303168,
                "file_path": "results\\MoveToPlayerTest2\\MoveToPlayer\\MoveToPlayer-303168.onnx",
                "reward": 14225.537465413412,
                "creation_time": 1742279378.9472713,
                "auxillary_file_paths": [
                    "results\\MoveToPlayerTest2\\MoveToPlayer\\MoveToPlayer-303168.pt"
                ]
            }
        ],
        "final_checkpoint": {
            "steps": 303168,
            "file_path": "results\\MoveToPlayerTest2\\MoveToPlayer.onnx",
            "reward": 14225.537465413412,
            "creation_time": 1742279378.9472713,
            "auxillary_file_paths": [
                "results\\MoveToPlayerTest2\\MoveToPlayer\\MoveToPlayer-303168.pt"
            ]
        }
    },
    "metadata": {
        "stats_format_version": "0.3.0",
        "mlagents_version": "1.1.0",
        "torch_version": "2.6.0+cu126"
    }
}